CHANGES.txt
LICENSE.txt
MANIFEST.in
README.rst
build-notes.txt
dev-requirements.txt
requirements.txt
setup.py
thumper/__init__.py
thumper/rabbit.py
thumper/runtests.py
thumper.egg-info/PKG-INFO
thumper.egg-info/SOURCES.txt
thumper.egg-info/dependency_links.txt
thumper.egg-info/requires.txt
thumper.egg-info/top_level.txt
thumper/test/__init__.py
thumper/test/test_mquri.py
thumper/test/test_thumper.py