Metadata-Version: 1.0
Name: thumper
Version: 0.0.11
Summary: Simplifies interactions with RabbitMQ by focusing on design patterns based on Topic Exchanges.
Home-page: https://bitbucket.org/dundeemt/thumper
Author: Jeff Hinrichs
Author-email: jeffh@dundeemt.com
License: LICENSE.txt
Platform: UNKNOWN
